weaver/__init__.py
weaver/settings.py
weaver/weaver.py
weaver/word.py
docx_weaver-0.1.0.dist-info/LICENSE
docx_weaver-0.1.0.dist-info/METADATA
docx_weaver-0.1.0.dist-info/WHEEL
docx_weaver-0.1.0.dist-info/top_level.txt
docx_weaver-0.1.0.dist-info/RECORD
